pysandboxes/__init__.py
pysandboxes-0.0.0.dist-info/METADATA
pysandboxes-0.0.0.dist-info/WHEEL
pysandboxes-0.0.0.dist-info/RECORD
