Metadata-Version: 2.3
Name: pysandboxes
Version: 0.0.0
Summary: Lite sandbox for python code execution
License: Apache 2.0
Author: Philippe PRADOS
Author-email: github@prados.fr
Requires-Python: >=3.13
Classifier: License :: Other/Proprietary License
Classifier: Programming Language :: Python :: 3
Classifier: Programming Language :: Python :: 3.13
Requires-Dist: dnspython (>=2.7.0)
Requires-Dist: interpreters-pep-734 ; python_version < "3.15"
Requires-Dist: langgraph (>=0.3.0)
